pypeform/__init__.py
pypeform/answer.py
pypeform/event.py
pypeform/field.py
pypeform/formresponse.py
pypeform/variable.py
pypeform_package-0.0.4.dist-info/METADATA
pypeform_package-0.0.4.dist-info/WHEEL
pypeform_package-0.0.4.dist-info/licenses/LICENSE
pypeform_package-0.0.4.dist-info/RECORD
