Metadata-Version: 2.1
Name: pypeform-package
Version: 0.0.4
Summary: Python Package for Typeform Response Piping
Project-URL: Homepage, https://github.com/vaxa-tech/pypeform
Project-URL: Bug Tracker, https://github.com/vaxa-tech/pypeform/issues
Author-email: Curtis West <curtis@curtiswest.net>
License: MIT License
Classifier: License :: OSI Approved :: MIT License
Classifier: Operating System :: OS Independent
Classifier: Programming Language :: Python :: 3
Requires-Python: >=3.7
Requires-Dist: flask
Requires-Dist: iso8601
Requires-Dist: pytz
Requires-Dist: requests
